[{"timestamp":"2021-12-01T18:18:16.214Z","count":67,"uniques":14},{"timestamp":"2022-01-01T18:17:37.038Z","count":128,"uniques":20},{"timestamp":"2022-02-01T18:18:13.475Z","count":242,"uniques":34},{"timestamp":"2022-03-01T18:19:06.900Z","count":81,"uniques":17},{"timestamp":"2022-04-01T01:24:35.748Z","count":105,"uniques":22},{"timestamp":"2022-05-01T18:19:23.251Z","count":43,"uniques":23},{"timestamp":"2022-06-01T18:23:05.694Z","count":23,"uniques":14},{"timestamp":"2022-07-01T18:19:42.946Z","count":42,"uniques":19},{"timestamp":"2022-08-01T01:52:59.011Z","count":21,"uniques":15},{"timestamp":"2022-09-01T01:51:44.150Z","count":14,"uniques":13},{"timestamp":"2022-10-01T01:52:22.110Z","count":37,"uniques":31},{"timestamp":"2022-11-01T01:09:11.760Z","count":21,"uniques":18},{"timestamp":"2022-12-01T18:18:47.609Z","count":19,"uniques":15}]
