[{"timestamp":"2022-11-21T01:34:10.358Z","count":0,"uniques":0},{"timestamp":"2022-11-22T01:33:17.483Z","count":0,"uniques":0},{"timestamp":"2022-11-23T01:23:48.457Z","count":0,"uniques":0},{"timestamp":"2022-11-24T01:35:42.031Z","count":0,"uniques":0},{"timestamp":"2022-11-25T01:23:51.301Z","count":0,"uniques":0},{"timestamp":"2022-11-26T01:19:13.062Z","count":0,"uniques":0},{"timestamp":"2022-11-27T01:32:09.049Z","count":0,"uniques":0},{"timestamp":"2022-11-28T01:23:01.232Z","count":0,"uniques":0},{"timestamp":"2022-11-29T01:25:01.136Z","count":0,"uniques":0},{"timestamp":"2022-11-30T01:25:37.061Z","count":0,"uniques":0},{"timestamp":"2022-12-01T01:31:23.796Z","count":0,"uniques":0},{"timestamp":"2022-12-02T01:20:27.679Z","count":0,"uniques":0},{"timestamp":"2022-12-03T01:18:51.099Z","count":0,"uniques":0},{"timestamp":"2022-12-04T01:21:00.220Z","count":0,"uniques":0},{"timestamp":"2022-12-05T01:18:10.521Z","count":0,"uniques":0},{"timestamp":"2022-12-06T01:19:41.540Z","count":0,"uniques":0},{"timestamp":"2022-12-07T01:22:58.720Z","count":0,"uniques":0},{"timestamp":"2022-12-08T01:20:25.993Z","count":0,"uniques":0},{"timestamp":"2022-12-09T01:20:37.637Z","count":0,"uniques":0},{"timestamp":"2022-12-10T01:15:58.132Z","count":0,"uniques":0},{"timestamp":"2022-12-11T01:25:52.896Z","count":0,"uniques":0},{"timestamp":"2022-12-12T01:21:09.478Z","count":0,"uniques":0},{"timestamp":"2022-12-13T01:24:58.553Z","count":0,"uniques":0},{"timestamp":"2022-12-14T01:19:35.219Z","count":0,"uniques":0},{"timestamp":"2022-12-15T01:21:59.125Z","count":0,"uniques":0},{"timestamp":"2022-12-16T01:16:05.580Z","count":0,"uniques":0},{"timestamp":"2022-12-17T01:22:30.442Z","count":0,"uniques":0},{"timestamp":"2022-12-18T01:16:30.042Z","count":0,"uniques":0},{"timestamp":"2022-12-19T01:14:10.554Z","count":0,"uniques":0},{"timestamp":"2022-12-20T01:18:35.051Z","count":0,"uniques":0},{"timestamp":"2022-12-21T01:17:04.610Z","count":0,"uniques":0},{"timestamp":"2022-12-22T01:21:44.187Z","count":0,"uniques":0},{"timestamp":"2022-12-23T01:16:10.661Z","count":0,"uniques":0},{"timestamp":"2022-12-24T01:12:34.742Z","count":0,"uniques":0},{"timestamp":"2022-12-25T01:20:07.458Z","count":0,"uniques":0},{"timestamp":"2022-12-26T01:16:46.891Z","count":0,"uniques":0},{"timestamp":"2022-12-27T01:16:53.893Z","count":0,"uniques":0},{"timestamp":"2022-12-28T01:15:46.580Z","count":0,"uniques":0},{"timestamp":"2022-12-29T01:17:44.222Z","count":0,"uniques":0},{"timestamp":"2022-12-30T01:19:07.303Z","count":0,"uniques":0},{"timestamp":"2022-12-31T01:19:49.252Z","count":0,"uniques":0},{"timestamp":"2023-01-01T01:29:13.338Z","count":0,"uniques":0},{"timestamp":"2023-01-02T01:18:25.431Z","count":0,"uniques":0},{"timestamp":"2023-01-03T01:16:52.529Z","count":0,"uniques":0},{"timestamp":"2023-01-04T01:18:48.099Z","count":0,"uniques":0},{"timestamp":"2023-01-05T01:19:14.729Z","count":0,"uniques":0},{"timestamp":"2023-01-06T01:28:28.443Z","count":0,"uniques":0},{"timestamp":"2023-01-07T01:17:37.499Z","count":0,"uniques":0},{"timestamp":"2023-01-08T01:28:40.879Z","count":0,"uniques":0},{"timestamp":"2023-01-09T01:18:08.754Z","count":0,"uniques":0},{"timestamp":"2023-01-10T01:22:22.362Z","count":0,"uniques":0},{"timestamp":"2023-01-11T01:24:58.938Z","count":0,"uniques":0},{"timestamp":"2023-01-12T01:21:03.833Z","count":0,"uniques":0},{"timestamp":"2023-01-13T01:26:40.644Z","count":0,"uniques":0},{"timestamp":"2023-01-14T01:20:57.662Z","count":0,"uniques":0},{"timestamp":"2023-01-15T01:23:18.092Z","count":0,"uniques":0},{"timestamp":"2023-01-16T18:35:12.514Z","count":0,"uniques":0},{"timestamp":"2023-01-17T01:23:22.483Z","count":0,"uniques":0},{"timestamp":"2023-01-18T01:21:20.958Z","count":0,"uniques":0},{"timestamp":"2023-01-19T01:25:26.588Z","count":0,"uniques":0},{"timestamp":"2023-01-20T01:19:51.464Z","count":0,"uniques":0},{"timestamp":"2023-01-21T01:20:07.572Z","count":0,"uniques":0},{"timestamp":"2023-01-22T01:22:49.921Z","count":0,"uniques":0},{"timestamp":"2023-01-23T01:17:12.822Z","count":0,"uniques":0},{"timestamp":"2023-01-24T01:32:52.429Z","count":0,"uniques":0},{"timestamp":"2023-01-25T01:16:33.805Z","count":0,"uniques":0},{"timestamp":"2023-01-26T01:21:37.999Z","count":0,"uniques":0},{"timestamp":"2023-01-27T01:28:12.116Z","count":0,"uniques":0},{"timestamp":"2023-01-28T01:20:35.150Z","count":0,"uniques":0},{"timestamp":"2023-01-29T01:25:12.277Z","count":0,"uniques":0},{"timestamp":"2023-01-30T01:15:48.596Z","count":0,"uniques":0},{"timestamp":"2023-01-31T01:23:49.030Z","count":0,"uniques":0},{"timestamp":"2023-02-01T01:27:56.175Z","count":0,"uniques":0},{"timestamp":"2023-02-02T01:22:09.926Z","count":0,"uniques":0},{"timestamp":"2023-02-03T01:22:23.252Z","count":0,"uniques":0},{"timestamp":"2023-02-04T01:17:12.326Z","count":0,"uniques":0},{"timestamp":"2023-02-05T01:25:38.169Z","count":0,"uniques":0},{"timestamp":"2023-02-06T01:17:39.231Z","count":0,"uniques":0},{"timestamp":"2023-02-07T01:19:35.564Z","count":0,"uniques":0},{"timestamp":"2023-02-08T01:20:19.612Z","count":0,"uniques":0},{"timestamp":"2023-02-09T01:23:50.421Z","count":0,"uniques":0},{"timestamp":"2023-02-10T01:24:15.449Z","count":0,"uniques":0},{"timestamp":"2023-02-11T01:17:47.855Z","count":0,"uniques":0},{"timestamp":"2023-02-12T01:26:02.439Z","count":0,"uniques":0},{"timestamp":"2023-02-13T01:24:25.565Z","count":0,"uniques":0},{"timestamp":"2023-02-14T01:24:40.303Z","count":0,"uniques":0},{"timestamp":"2023-02-15T01:29:59.943Z","count":0,"uniques":0},{"timestamp":"2023-02-16T01:22:51.408Z","count":0,"uniques":0},{"timestamp":"2023-02-17T01:32:25.067Z","count":0,"uniques":0},{"timestamp":"2023-02-18T01:21:41.566Z","count":0,"uniques":0},{"timestamp":"2023-02-19T01:24:48.860Z","count":0,"uniques":0},{"timestamp":"2023-02-20T01:29:59.599Z","count":0,"uniques":0},{"timestamp":"2023-02-21T01:26:40.892Z","count":0,"uniques":0},{"timestamp":"2023-02-22T01:24:32.563Z","count":0,"uniques":0},{"timestamp":"2023-02-23T01:21:09.250Z","count":0,"uniques":0},{"timestamp":"2023-02-24T01:29:06.154Z","count":0,"uniques":0},{"timestamp":"2023-02-25T01:22:08.194Z","count":0,"uniques":0},{"timestamp":"2023-02-26T01:30:07.313Z","count":0,"uniques":0},{"timestamp":"2023-02-27T01:24:44.306Z","count":0,"uniques":0},{"timestamp":"2023-02-28T18:38:24.397Z","count":0,"uniques":0},{"timestamp":"2023-03-01T01:31:04.087Z","count":0,"uniques":0},{"timestamp":"2023-03-02T01:27:56.276Z","count":0,"uniques":0},{"timestamp":"2023-03-03T03:18:50.188Z","count":0,"uniques":0},{"timestamp":"2023-03-04T01:21:54.123Z","count":0,"uniques":0},{"timestamp":"2023-03-05T01:31:36.417Z","count":0,"uniques":0},{"timestamp":"2023-03-06T01:23:28.332Z","count":0,"uniques":0},{"timestamp":"2023-03-07T01:28:17.462Z","count":0,"uniques":0},{"timestamp":"2023-03-08T01:27:43.807Z","count":0,"uniques":0},{"timestamp":"2023-03-09T01:26:16.008Z","count":0,"uniques":0},{"timestamp":"2023-03-10T01:25:33.088Z","count":0,"uniques":0},{"timestamp":"2023-03-11T01:15:22.542Z","count":0,"uniques":0},{"timestamp":"2023-03-12T01:25:31.404Z","count":0,"uniques":0},{"timestamp":"2023-03-13T01:21:36.723Z","count":0,"uniques":0},{"timestamp":"2023-03-14T01:16:06.072Z","count":0,"uniques":0},{"timestamp":"2023-03-15T01:27:13.810Z","count":0,"uniques":0},{"timestamp":"2023-03-16T01:27:10.037Z","count":0,"uniques":0},{"timestamp":"2023-03-17T01:21:47.073Z","count":0,"uniques":0},{"timestamp":"2023-03-18T01:19:03.883Z","count":0,"uniques":0},{"timestamp":"2023-03-19T01:33:10.096Z","count":0,"uniques":0},{"timestamp":"2023-03-20T01:24:03.989Z","count":0,"uniques":0},{"timestamp":"2023-03-21T01:18:19.605Z","count":0,"uniques":0},{"timestamp":"2023-03-22T01:16:34.679Z","count":0,"uniques":0},{"timestamp":"2023-03-23T01:18:33.878Z","count":0,"uniques":0},{"timestamp":"2023-03-24T01:21:58.359Z","count":0,"uniques":0},{"timestamp":"2023-03-25T01:16:55.045Z","count":0,"uniques":0},{"timestamp":"2023-03-26T01:23:20.920Z","count":0,"uniques":0},{"timestamp":"2023-03-27T01:16:10.558Z","count":0,"uniques":0},{"timestamp":"2023-03-28T01:19:20.042Z","count":0,"uniques":0},{"timestamp":"2023-03-29T01:23:29.278Z","count":0,"uniques":0},{"timestamp":"2023-03-30T01:26:30.742Z","count":0,"uniques":0},{"timestamp":"2023-03-31T01:20:18.457Z","count":0,"uniques":0},{"timestamp":"2023-04-01T01:17:25.965Z","count":0,"uniques":0},{"timestamp":"2023-04-02T01:22:54.483Z","count":0,"uniques":0},{"timestamp":"2023-04-03T01:14:28.638Z","count":0,"uniques":0},{"timestamp":"2023-04-04T01:24:24.153Z","count":0,"uniques":0},{"timestamp":"2023-04-05T01:10:03.929Z","count":0,"uniques":0},{"timestamp":"2023-04-06T01:13:56.726Z","count":0,"uniques":0},{"timestamp":"2023-04-07T01:16:13.786Z","count":0,"uniques":0},{"timestamp":"2023-04-08T01:13:09.194Z","count":0,"uniques":0},{"timestamp":"2023-04-09T01:16:03.236Z","count":0,"uniques":0},{"timestamp":"2023-04-10T01:13:55.587Z","count":0,"uniques":0},{"timestamp":"2023-04-11T01:18:58.753Z","count":0,"uniques":0},{"timestamp":"2023-04-12T01:15:13.882Z","count":0,"uniques":0},{"timestamp":"2023-04-13T01:12:38.389Z","count":0,"uniques":0},{"timestamp":"2023-04-14T01:19:44.356Z","count":0,"uniques":0},{"timestamp":"2023-04-15T01:16:27.432Z","count":0,"uniques":0},{"timestamp":"2023-04-16T01:20:18.098Z","count":0,"uniques":0},{"timestamp":"2023-04-17T01:23:18.552Z","count":0,"uniques":0},{"timestamp":"2023-04-18T01:16:00.384Z","count":0,"uniques":0},{"timestamp":"2023-04-19T01:18:15.479Z","count":0,"uniques":0},{"timestamp":"2023-04-20T01:17:46.152Z","count":0,"uniques":0},{"timestamp":"2023-04-21T01:14:28.305Z","count":0,"uniques":0},{"timestamp":"2023-04-22T01:15:39.441Z","count":0,"uniques":0},{"timestamp":"2023-04-23T01:27:30.610Z","count":0,"uniques":0},{"timestamp":"2023-04-24T01:17:55.536Z","count":0,"uniques":0},{"timestamp":"2023-04-25T01:16:37.655Z","count":0,"uniques":0},{"timestamp":"2023-04-26T01:16:13.041Z","count":0,"uniques":0},{"timestamp":"2023-04-27T01:17:31.441Z","count":0,"uniques":0},{"timestamp":"2023-04-28T01:17:14.530Z","count":0,"uniques":0},{"timestamp":"2023-04-29T01:18:05.484Z","count":0,"uniques":0},{"timestamp":"2023-04-30T01:21:54.604Z","count":0,"uniques":0},{"timestamp":"2023-05-01T01:20:19.304Z","count":0,"uniques":0},{"timestamp":"2023-05-02T01:18:20.454Z","count":0,"uniques":0},{"timestamp":"2023-05-03T01:17:22.462Z","count":0,"uniques":0},{"timestamp":"2023-05-04T01:15:16.662Z","count":0,"uniques":0},{"timestamp":"2023-05-05T01:16:11.727Z","count":0,"uniques":0},{"timestamp":"2023-05-06T01:14:31.078Z","count":0,"uniques":0},{"timestamp":"2023-05-07T01:22:20.331Z","count":0,"uniques":0},{"timestamp":"2023-05-08T01:18:08.632Z","count":0,"uniques":0},{"timestamp":"2023-05-09T01:21:38.899Z","count":0,"uniques":0},{"timestamp":"2023-05-10T01:16:20.718Z","count":0,"uniques":0},{"timestamp":"2023-05-11T01:16:04.505Z","count":0,"uniques":0},{"timestamp":"2023-05-12T01:15:34.766Z","count":0,"uniques":0},{"timestamp":"2023-05-13T01:13:11.849Z","count":0,"uniques":0},{"timestamp":"2023-05-14T01:22:09.288Z","count":0,"uniques":0},{"timestamp":"2023-05-15T01:17:21.907Z","count":0,"uniques":0},{"timestamp":"2023-05-16T01:18:41.890Z","count":0,"uniques":0},{"timestamp":"2023-05-17T01:19:08.433Z","count":0,"uniques":0},{"timestamp":"2023-05-18T01:15:56.818Z","count":0,"uniques":0},{"timestamp":"2023-05-19T01:21:05.609Z","count":0,"uniques":0},{"timestamp":"2023-05-20T01:19:22.114Z","count":0,"uniques":0},{"timestamp":"2023-05-21T01:21:36.921Z","count":0,"uniques":0},{"timestamp":"2023-05-22T01:21:45.043Z","count":0,"uniques":0},{"timestamp":"2023-05-23T01:17:42.158Z","count":0,"uniques":0},{"timestamp":"2023-05-24T01:36:02.456Z","count":0,"uniques":0},{"timestamp":"2023-05-25T01:36:01.006Z","count":0,"uniques":0},{"timestamp":"2023-05-26T01:21:02.794Z","count":0,"uniques":0},{"timestamp":"2023-05-27T01:19:36.369Z","count":0,"uniques":0},{"timestamp":"2023-05-28T01:26:03.422Z","count":0,"uniques":0},{"timestamp":"2023-05-29T01:24:52.322Z","count":0,"uniques":0},{"timestamp":"2023-05-30T01:24:06.605Z","count":0,"uniques":0},{"timestamp":"2023-05-31T01:25:35.303Z","count":0,"uniques":0},{"timestamp":"2023-06-01T01:40:17.270Z","count":0,"uniques":0},{"timestamp":"2023-06-02T01:32:24.694Z","count":0,"uniques":0},{"timestamp":"2023-06-03T01:24:38.851Z","count":0,"uniques":0},{"timestamp":"2023-06-04T01:40:07.891Z","count":0,"uniques":0},{"timestamp":"2023-06-05T01:27:01.257Z","count":0,"uniques":0},{"timestamp":"2023-06-06T01:26:57.026Z","count":0,"uniques":0},{"timestamp":"2023-06-07T01:28:55.876Z","count":0,"uniques":0},{"timestamp":"2023-06-08T01:26:15.688Z","count":0,"uniques":0},{"timestamp":"2023-06-09T01:27:47.657Z","count":0,"uniques":0},{"timestamp":"2023-06-10T01:22:43.833Z","count":0,"uniques":0},{"timestamp":"2023-06-11T01:40:39.459Z","count":0,"uniques":0},{"timestamp":"2023-06-12T01:30:02.680Z","count":0,"uniques":0},{"timestamp":"2023-06-13T01:24:21.488Z","count":0,"uniques":0},{"timestamp":"2023-06-14T01:22:28.706Z","count":0,"uniques":0},{"timestamp":"2023-06-15T01:33:02.735Z","count":0,"uniques":0},{"timestamp":"2023-06-16T01:29:33.505Z","count":0,"uniques":0},{"timestamp":"2023-06-17T01:19:04.929Z","count":0,"uniques":0},{"timestamp":"2023-06-18T01:31:56.685Z","count":0,"uniques":0},{"timestamp":"2023-06-19T01:26:58.602Z","count":0,"uniques":0},{"timestamp":"2023-06-20T01:24:56.709Z","count":0,"uniques":0},{"timestamp":"2023-06-21T01:24:13.693Z","count":0,"uniques":0},{"timestamp":"2023-06-22T01:27:29.961Z","count":0,"uniques":0},{"timestamp":"2023-06-23T01:30:51.786Z","count":0,"uniques":0},{"timestamp":"2023-06-24T01:37:28.933Z","count":0,"uniques":0},{"timestamp":"2023-06-25T01:39:19.829Z","count":0,"uniques":0},{"timestamp":"2023-06-26T01:34:03.269Z","count":0,"uniques":0},{"timestamp":"2023-06-27T01:32:29.438Z","count":0,"uniques":0},{"timestamp":"2023-06-28T01:39:50.032Z","count":0,"uniques":0},{"timestamp":"2023-06-29T01:30:01.437Z","count":0,"uniques":0},{"timestamp":"2023-06-30T01:29:40.332Z","count":0,"uniques":0},{"timestamp":"2023-07-01T01:37:44.240Z","count":0,"uniques":0},{"timestamp":"2023-07-02T01:36:45.677Z","count":0,"uniques":0},{"timestamp":"2023-07-03T01:33:38.418Z","count":0,"uniques":0},{"timestamp":"2023-07-04T01:37:51.734Z","count":0,"uniques":0},{"timestamp":"2023-07-05T01:33:36.566Z","count":0,"uniques":0},{"timestamp":"2023-07-06T01:37:08.779Z","count":0,"uniques":0},{"timestamp":"2023-07-07T01:39:07.689Z","count":0,"uniques":0},{"timestamp":"2023-07-08T01:39:25.652Z","count":0,"uniques":0},{"timestamp":"2023-07-09T01:37:06.906Z","count":0,"uniques":0},{"timestamp":"2023-07-10T01:39:50.026Z","count":0,"uniques":0},{"timestamp":"2023-07-11T01:25:32.270Z","count":0,"uniques":0},{"timestamp":"2023-07-12T01:34:22.850Z","count":0,"uniques":0},{"timestamp":"2023-07-13T01:37:31.037Z","count":0,"uniques":0},{"timestamp":"2023-07-14T01:37:59.278Z","count":0,"uniques":0},{"timestamp":"2023-07-15T01:32:15.847Z","count":0,"uniques":0},{"timestamp":"2023-07-16T01:40:53.345Z","count":0,"uniques":0},{"timestamp":"2023-07-17T01:38:35.858Z","count":0,"uniques":0},{"timestamp":"2023-07-18T01:57:13.562Z","count":0,"uniques":0},{"timestamp":"2023-07-19T02:42:46.078Z","count":0,"uniques":0},{"timestamp":"2023-07-20T01:22:27.301Z","count":0,"uniques":0},{"timestamp":"2023-07-21T01:23:34.705Z","count":0,"uniques":0},{"timestamp":"2023-07-22T01:28:27.364Z","count":0,"uniques":0},{"timestamp":"2023-07-23T01:26:11.497Z","count":0,"uniques":0},{"timestamp":"2023-07-24T01:22:03.920Z","count":0,"uniques":0},{"timestamp":"2023-07-25T01:33:22.920Z","count":0,"uniques":0},{"timestamp":"2023-07-26T01:27:55.431Z","count":0,"uniques":0},{"timestamp":"2023-07-27T01:15:49.466Z","count":0,"uniques":0},{"timestamp":"2023-07-28T01:22:04.136Z","count":0,"uniques":0},{"timestamp":"2023-07-29T01:18:22.132Z","count":0,"uniques":0},{"timestamp":"2023-07-30T01:22:05.238Z","count":0,"uniques":0},{"timestamp":"2023-07-31T01:19:44.918Z","count":0,"uniques":0},{"timestamp":"2023-08-01T01:26:48.231Z","count":0,"uniques":0},{"timestamp":"2023-08-02T01:15:18.929Z","count":0,"uniques":0},{"timestamp":"2023-08-03T01:23:33.185Z","count":0,"uniques":0},{"timestamp":"2023-08-04T01:18:11.037Z","count":0,"uniques":0},{"timestamp":"2023-08-05T01:21:23.825Z","count":0,"uniques":0},{"timestamp":"2023-08-06T01:11:36.317Z","count":0,"uniques":0},{"timestamp":"2023-08-07T01:18:26.816Z","count":0,"uniques":0},{"timestamp":"2023-08-08T01:15:36.208Z","count":0,"uniques":0},{"timestamp":"2023-08-09T01:17:34.143Z","count":0,"uniques":0},{"timestamp":"2023-08-10T01:17:34.493Z","count":0,"uniques":0},{"timestamp":"2023-08-11T01:11:20.814Z","count":0,"uniques":0},{"timestamp":"2023-08-12T01:08:14.049Z","count":0,"uniques":0},{"timestamp":"2023-08-13T01:14:16.949Z","count":0,"uniques":0},{"timestamp":"2023-08-14T01:10:06.399Z","count":0,"uniques":0},{"timestamp":"2023-08-15T01:05:42.064Z","count":0,"uniques":0},{"timestamp":"2023-08-16T01:05:58.029Z","count":0,"uniques":0},{"timestamp":"2023-08-17T01:09:58.969Z","count":0,"uniques":0},{"timestamp":"2023-08-18T01:06:55.252Z","count":0,"uniques":0},{"timestamp":"2023-08-19T01:10:47.918Z","count":0,"uniques":0},{"timestamp":"2023-08-20T01:12:42.663Z","count":0,"uniques":0},{"timestamp":"2023-08-21T01:05:24.703Z","count":0,"uniques":0},{"timestamp":"2023-08-22T01:09:19.942Z","count":0,"uniques":0},{"timestamp":"2023-08-23T01:05:12.438Z","count":0,"uniques":0},{"timestamp":"2023-08-24T01:05:08.904Z","count":0,"uniques":0},{"timestamp":"2023-08-25T01:07:15.050Z","count":0,"uniques":0},{"timestamp":"2023-08-26T01:11:26.239Z","count":0,"uniques":0},{"timestamp":"2023-08-27T01:09:26.423Z","count":0,"uniques":0},{"timestamp":"2023-08-28T01:08:24.234Z","count":0,"uniques":0},{"timestamp":"2023-08-29T01:13:53.994Z","count":0,"uniques":0},{"timestamp":"2023-08-30T01:06:48.490Z","count":0,"uniques":0},{"timestamp":"2023-08-31T01:07:12.951Z","count":0,"uniques":0},{"timestamp":"2023-09-01T01:09:55.027Z","count":0,"uniques":0},{"timestamp":"2023-09-02T01:05:35.374Z","count":0,"uniques":0},{"timestamp":"2023-09-03T01:11:57.202Z","count":0,"uniques":0},{"timestamp":"2023-09-04T01:07:46.542Z","count":0,"uniques":0},{"timestamp":"2023-09-05T01:12:31.122Z","count":0,"uniques":0},{"timestamp":"2023-09-06T01:13:18.102Z","count":0,"uniques":0},{"timestamp":"2023-09-07T01:07:08.309Z","count":0,"uniques":0},{"timestamp":"2023-09-08T01:10:33.808Z","count":0,"uniques":0},{"timestamp":"2023-09-09T01:08:52.699Z","count":0,"uniques":0},{"timestamp":"2023-09-10T01:15:38.161Z","count":0,"uniques":0},{"timestamp":"2023-09-11T01:07:21.990Z","count":0,"uniques":0},{"timestamp":"2023-09-12T01:07:29.900Z","count":0,"uniques":0},{"timestamp":"2023-09-13T01:08:05.835Z","count":0,"uniques":0},{"timestamp":"2023-09-14T01:07:49.278Z","count":0,"uniques":0},{"timestamp":"2023-09-15T01:09:19.709Z","count":0,"uniques":0},{"timestamp":"2023-09-16T01:06:48.997Z","count":0,"uniques":0},{"timestamp":"2023-09-17T01:10:15.070Z","count":0,"uniques":0},{"timestamp":"2023-09-18T01:08:17.595Z","count":0,"uniques":0},{"timestamp":"2023-09-19T01:08:41.126Z","count":0,"uniques":0},{"timestamp":"2023-09-20T01:10:26.564Z","count":0,"uniques":0},{"timestamp":"2023-09-21T01:15:35.961Z","count":0,"uniques":0},{"timestamp":"2023-09-22T01:09:03.540Z","count":0,"uniques":0},{"timestamp":"2023-09-23T01:06:31.431Z","count":0,"uniques":0},{"timestamp":"2023-09-24T01:17:14.999Z","count":0,"uniques":0},{"timestamp":"2023-09-25T01:08:11.791Z","count":0,"uniques":0},{"timestamp":"2023-09-26T01:12:01.790Z","count":0,"uniques":0},{"timestamp":"2023-09-27T01:13:07.023Z","count":0,"uniques":0},{"timestamp":"2023-09-28T01:14:08.761Z","count":0,"uniques":0},{"timestamp":"2023-09-29T01:09:44.026Z","count":0,"uniques":0},{"timestamp":"2023-09-30T01:06:50.935Z","count":0,"uniques":0},{"timestamp":"2023-10-01T01:16:22.525Z","count":0,"uniques":0},{"timestamp":"2023-10-02T01:08:40.610Z","count":0,"uniques":0},{"timestamp":"2023-10-03T01:10:07.595Z","count":0,"uniques":0},{"timestamp":"2023-10-04T01:14:56.337Z","count":0,"uniques":0},{"timestamp":"2023-10-05T01:08:21.890Z","count":0,"uniques":0},{"timestamp":"2023-10-06T01:07:34.448Z","count":0,"uniques":0},{"timestamp":"2023-10-07T01:11:02.382Z","count":0,"uniques":0},{"timestamp":"2023-10-08T01:11:24.323Z","count":0,"uniques":0},{"timestamp":"2023-10-09T01:09:41.895Z","count":0,"uniques":0},{"timestamp":"2023-10-10T01:12:50.940Z","count":0,"uniques":0},{"timestamp":"2023-10-11T01:08:19.476Z","count":0,"uniques":0},{"timestamp":"2023-10-12T01:05:58.131Z","count":0,"uniques":0},{"timestamp":"2023-10-13T01:10:01.807Z","count":0,"uniques":0},{"timestamp":"2023-10-14T01:08:29.723Z","count":0,"uniques":0},{"timestamp":"2023-10-15T01:13:12.391Z","count":0,"uniques":0},{"timestamp":"2023-10-16T01:12:19.675Z","count":0,"uniques":0},{"timestamp":"2023-10-17T01:08:48.739Z","count":0,"uniques":0},{"timestamp":"2023-10-18T01:12:28.030Z","count":0,"uniques":0},{"timestamp":"2023-10-19T01:09:22.728Z","count":0,"uniques":0},{"timestamp":"2023-10-20T01:13:25.806Z","count":0,"uniques":0},{"timestamp":"2023-10-21T01:10:18.226Z","count":0,"uniques":0},{"timestamp":"2023-10-22T01:11:21.179Z","count":0,"uniques":0},{"timestamp":"2023-10-23T01:08:51.790Z","count":0,"uniques":0},{"timestamp":"2023-10-24T01:12:49.102Z","count":0,"uniques":0},{"timestamp":"2023-10-25T01:12:20.172Z","count":0,"uniques":0},{"timestamp":"2023-10-26T01:08:45.709Z","count":0,"uniques":0},{"timestamp":"2023-10-27T01:07:27.216Z","count":0,"uniques":0},{"timestamp":"2023-10-28T01:13:17.304Z","count":0,"uniques":0},{"timestamp":"2023-10-29T01:11:28.907Z","count":0,"uniques":0},{"timestamp":"2023-10-30T01:10:22.755Z","count":0,"uniques":0},{"timestamp":"2023-10-31T01:15:29.024Z","count":0,"uniques":0},{"timestamp":"2023-11-01T01:14:49.962Z","count":0,"uniques":0},{"timestamp":"2023-11-02T01:14:13.122Z","count":0,"uniques":0},{"timestamp":"2023-11-03T01:10:07.009Z","count":0,"uniques":0},{"timestamp":"2023-11-04T01:05:19.563Z","count":0,"uniques":0},{"timestamp":"2023-11-05T01:12:08.541Z","count":0,"uniques":0},{"timestamp":"2023-11-06T01:07:04.262Z","count":0,"uniques":0},{"timestamp":"2023-11-07T01:07:00.447Z","count":0,"uniques":0},{"timestamp":"2023-11-08T01:11:58.662Z","count":0,"uniques":0},{"timestamp":"2023-11-09T01:10:49.319Z","count":0,"uniques":0},{"timestamp":"2023-11-10T01:05:54.786Z","count":0,"uniques":0},{"timestamp":"2023-11-11T01:11:30.522Z","count":0,"uniques":0},{"timestamp":"2023-11-12T01:16:16.778Z","count":0,"uniques":0},{"timestamp":"2023-11-13T01:16:29.304Z","count":0,"uniques":0},{"timestamp":"2023-11-14T01:05:54.127Z","count":0,"uniques":0},{"timestamp":"2023-11-15T01:07:17.444Z","count":0,"uniques":0},{"timestamp":"2023-11-16T01:09:21.269Z","count":0,"uniques":0},{"timestamp":"2023-11-17T01:07:55.417Z","count":0,"uniques":0},{"timestamp":"2023-11-18T01:07:56.992Z","count":0,"uniques":0},{"timestamp":"2023-11-19T01:11:20.692Z","count":0,"uniques":0},{"timestamp":"2023-11-20T01:09:15.428Z","count":0,"uniques":0},{"timestamp":"2023-11-21T01:08:47.271Z","count":0,"uniques":0}]
