[{"timestamp":"2023-11-01T01:11:43.499Z","count":0,"uniques":0},{"timestamp":"2023-12-01T01:07:27.347Z","count":9,"uniques":9},{"timestamp":"2024-01-01T01:06:28.594Z","count":4,"uniques":4},{"timestamp":"2024-02-01T01:03:29.198Z","count":0,"uniques":0},{"timestamp":"2024-03-01T18:25:02.226Z","count":6,"uniques":4},{"timestamp":"2024-04-01T01:05:09.058Z","count":6,"uniques":4},{"timestamp":"2024-05-01T01:07:15.295Z","count":0,"uniques":0},{"timestamp":"2024-06-01T01:12:41.598Z","count":0,"uniques":0},{"timestamp":"2024-07-01T01:11:20.686Z","count":0,"uniques":0},{"timestamp":"2024-08-01T01:14:42.946Z","count":0,"uniques":0},{"timestamp":"2024-09-01T01:18:41.125Z","count":0,"uniques":0},{"timestamp":"2024-10-01T01:22:58.184Z","count":0,"uniques":0},{"timestamp":"2024-11-01T01:20:58.382Z","count":0,"uniques":0}]
