[{"timestamp":"2023-08-01T18:25:06.115Z","count":101,"uniques":9},{"timestamp":"2023-09-01T18:24:09.885Z","count":80,"uniques":8},{"timestamp":"2023-10-01T01:06:43.927Z","count":64,"uniques":7},{"timestamp":"2023-11-01T01:07:38.542Z","count":15,"uniques":6},{"timestamp":"2023-12-01T18:21:19.568Z","count":61,"uniques":7},{"timestamp":"2024-01-01T18:21:04.166Z","count":83,"uniques":10},{"timestamp":"2024-02-01T18:22:22.175Z","count":29,"uniques":4},{"timestamp":"2024-03-01T18:22:30.608Z","count":57,"uniques":8},{"timestamp":"2024-04-01T18:24:23.278Z","count":267,"uniques":14},{"timestamp":"2024-05-01T18:23:20.923Z","count":18,"uniques":3},{"timestamp":"2024-06-01T18:24:14.250Z","count":13,"uniques":3},{"timestamp":"2024-07-01T18:25:35.310Z","count":20,"uniques":5}]
