[{"timestamp":"2023-01-01T01:26:20.262Z","count":11,"uniques":5},{"timestamp":"2023-02-01T18:44:08.827Z","count":2,"uniques":2},{"timestamp":"2023-03-01T18:35:57.697Z","count":5,"uniques":5},{"timestamp":"2023-04-01T18:33:22.129Z","count":3,"uniques":3},{"timestamp":"2023-05-01T18:35:00.607Z","count":9,"uniques":6},{"timestamp":"2023-06-01T18:35:25.831Z","count":3,"uniques":3},{"timestamp":"2023-07-01T02:47:02.003Z","count":3,"uniques":3},{"timestamp":"2023-08-01T18:34:41.087Z","count":13,"uniques":7},{"timestamp":"2023-09-01T18:34:07.707Z","count":6,"uniques":4},{"timestamp":"2023-10-01T18:40:39.638Z","count":19,"uniques":4},{"timestamp":"2023-11-01T18:30:33.936Z","count":8,"uniques":6},{"timestamp":"2023-12-01T18:29:53.941Z","count":2,"uniques":2},{"timestamp":"2024-01-01T01:09:34.730Z","count":0,"uniques":0}]
