[{"timestamp":"2021-05-01T19:27:15.338Z","count":0,"uniques":0},{"timestamp":"2021-06-01T19:27:15.338Z","count":0,"uniques":0},{"timestamp":"2021-07-01T19:27:15.338Z","count":0,"uniques":0},{"timestamp":"2021-08-01T19:27:15.338Z","count":0,"uniques":0},{"timestamp":"2021-09-01T19:27:15.338Z","count":0,"uniques":0},{"timestamp":"2021-10-01T19:27:15.338Z","count":0,"uniques":0},{"timestamp":"2021-11-01T19:27:15.338Z","count":1,"uniques":1},{"timestamp":"2021-12-01T18:17:40.385Z","count":62,"uniques":8},{"timestamp":"2022-01-01T18:25:53.998Z","count":85,"uniques":14},{"timestamp":"2022-02-01T18:27:49.178Z","count":60,"uniques":10},{"timestamp":"2022-03-01T18:27:01.806Z","count":88,"uniques":21},{"timestamp":"2022-04-01T18:26:48.709Z","count":88,"uniques":20},{"timestamp":"2022-05-01T18:27:53.139Z","count":83,"uniques":11}]
