[{"timestamp":"2021-10-01T19:33:37.212Z","count":0,"uniques":0},{"timestamp":"2021-11-01T19:33:37.212Z","count":0,"uniques":0},{"timestamp":"2021-12-01T19:33:37.212Z","count":0,"uniques":0},{"timestamp":"2022-01-01T00:34:07.060Z","count":0,"uniques":0},{"timestamp":"2022-02-01T00:52:12.721Z","count":0,"uniques":0},{"timestamp":"2022-03-01T18:22:01.164Z","count":6,"uniques":1},{"timestamp":"2022-04-01T18:21:20.458Z","count":8,"uniques":2},{"timestamp":"2022-05-01T01:21:19.373Z","count":0,"uniques":0},{"timestamp":"2022-06-01T01:24:25.364Z","count":0,"uniques":0},{"timestamp":"2022-07-01T01:21:13.460Z","count":0,"uniques":0},{"timestamp":"2022-08-01T01:52:07.992Z","count":0,"uniques":0},{"timestamp":"2022-09-01T01:45:17.575Z","count":0,"uniques":0},{"timestamp":"2022-10-01T01:56:29.318Z","count":0,"uniques":0}]
